helperfns/__init__.py
helperfns/static/.keep
helperfns/static/images/apple.png
helperfns/static/images/chicken.png
helperfns/static/images/head.png
helperfns/static/images/tree.png
helperfns/static/images/wine.png
helperfns/tables/__init__.py
helperfns/tests/tables/test_tables.py
helperfns/tests/text/test_text.py
helperfns/tests/utils/test_utils.py
helperfns/tests/visualization/test_visualization.py
helperfns/text/__init__.py
helperfns/utils/__init__.py
helperfns/visualization/__init__.py
helperfns-1.2.1.dist-info/LICENSE
helperfns-1.2.1.dist-info/METADATA
helperfns-1.2.1.dist-info/WHEEL
helperfns-1.2.1.dist-info/top_level.txt
helperfns-1.2.1.dist-info/RECORD
