Metadata-Version: 2.1
Name: helperfns
Version: 1.2.1
Summary: This package provides some Python helper functions that are useful in machine learning.
Author-email: Crispen Gari <crispengari@gmail.com>
License: MIT License
Project-URL: homepage, https://github.com/CrispenGari/helperfns
Project-URL: repository, https://github.com/CrispenGari/helperfns
Project-URL: documentation, https://github.com/CrispenGari/helperfns/blob/main/README.md
Project-URL: changelog, https://github.com/CrispenGari/helperfns/blob/main/CHANGELOG.md
Project-URL: issues, https://github.com/CrispenGari/helperfns/issues
Keywords: helperfns,python,python3,helper-functions,text cleaning,visualization,machine-learning
Classifier: Development Status :: 5 - Production/Stable
Classifier: Intended Audience :: Developers
Classifier: Programming Language :: Python :: 3.12
Classifier: Operating System :: Unix
Classifier: Operating System :: MacOS :: MacOS X
Classifier: Operating System :: Microsoft :: Windows
Classifier: Natural Language :: English
Requires-Python: >=3.10
License-File: LICENSE
Requires-Dist: prettytable
Requires-Dist: nltk
Requires-Dist: scikit-learn
Requires-Dist: matplotlib
Requires-Dist: numpy
Requires-Dist: pandas
Requires-Dist: seaborn
Requires-Dist: wordcloud
